classparse/__init__.py
classparse/docs.py
classparse/types.py
classparse-0.1.4.dist-info/LICENSE
classparse-0.1.4.dist-info/METADATA
classparse-0.1.4.dist-info/WHEEL
classparse-0.1.4.dist-info/top_level.txt
classparse-0.1.4.dist-info/RECORD
