Metadata-Version: 2.1
Name: classparse
Version: 0.1.4
Summary: Declarative `ArgumentParser` definition with `dataclass` notation.
Author-email: Liran Funaro <liran.funaro@gmail.com>
License: BSD-3-Clause
Project-URL: Homepage, https://github.com/liran-funaro/classparse
Keywords: argparse,dataclass
Classifier: Programming Language :: Python
Classifier: Programming Language :: Python :: 3
Classifier: License :: OSI Approved :: BSD License
Classifier: Operating System :: OS Independent
Classifier: Topic :: Software Development :: Libraries :: Python Modules
Requires-Python: >=3.8
License-File: LICENSE
Requires-Dist: PyYAML
Provides-Extra: dev
Requires-Dist: bumpver ; extra == 'dev'
Requires-Dist: black ; extra == 'dev'
Requires-Dist: isort ; extra == 'dev'
Requires-Dist: flake8 ; extra == 'dev'
Requires-Dist: pip-tools ; extra == 'dev'
Requires-Dist: pytest ; extra == 'dev'
Requires-Dist: pytest-cov ; extra == 'dev'
Requires-Dist: coveralls ; extra == 'dev'
